{
    "OBIO": {
        "610": {
            "600": {
                "grade_amount": {
                    "A": "12",
                    "B": "0",
                    "C": "0",
                    "D": "0",
                    "F": "0"
                },
                "grade_percentage": {
                    "A": "100.00",
                    "B": "0.00",
                    "C": "0.00",
                    "D": "0.00",
                    "F": "0.00"
                },
                "total": "12",
                "gpa": "4.000",
                "other": {
                    "I": "0",
                    "S": "0",
                    "U": "0",
                    "Q": "0",
                    "X": "0",
                    "total": "12"
                },
                "professor": "LIU X"
            }
        },
        "611": {
            "600": {
                "grade_amount": {
                    "A": "20",
                    "B": "7",
                    "C": "0",
                    "D": "0",
                    "F": "0"
                },
                "grade_percentage": {
                    "A": "74.07",
                    "B": "25.93",
                    "C": "0.00",
                    "D": "0.00",
                    "F": "0.00"
                },
                "total": "27",
                "gpa": "3.740",
                "other": {
                    "I": "0",
                    "S": "0",
                    "U": "0",
                    "Q": "0",
                    "X": "0",
                    "total": "27"
                },
                "professor": "BUSCHANG P"
            }
        },
        "630": {
            "600": {
                "grade_amount": {
                    "A": "14",
                    "B": "2",
                    "C": "0",
                    "D": "0",
                    "F": "0"
                },
                "grade_percentage": {
                    "A": "87.50",
                    "B": "12.50",
                    "C": "0.00",
                    "D": "0.00",
                    "F": "0.00"
                },
                "total": "16",
                "gpa": "3.875",
                "other": {
                    "I": "0",
                    "S": "0",
                    "U": "0",
                    "Q": "0",
                    "X": "0",
                    "total": "16"
                },
                "professor": "RUEST L"
            }
        },
        "631": {
            "600": {
                "grade_amount": {
                    "A": "18",
                    "B": "2",
                    "C": "0",
                    "D": "0",
                    "F": "0"
                },
                "grade_percentage": {
                    "A": "90.00",
                    "B": "10.00",
                    "C": "0.00",
                    "D": "0.00",
                    "F": "0.00"
                },
                "total": "20",
                "gpa": "3.900",
                "other": {
                    "I": "0",
                    "S": "0",
                    "U": "0",
                    "Q": "0",
                    "X": "0",
                    "total": "20"
                },
                "professor": "RUEST L"
            }
        },
        "674": {
            "600": {
                "grade_amount": {
                    "A": "8",
                    "B": "0",
                    "C": "0",
                    "D": "0",
                    "F": "0"
                },
                "grade_percentage": {
                    "A": "100.00",
                    "B": "0.00",
                    "C": "0.00",
                    "D": "0.00",
                    "F": "0.00"
                },
                "total": "8",
                "gpa": "4.000",
                "other": {
                    "I": "0",
                    "S": "0",
                    "U": "0",
                    "Q": "0",
                    "X": "0",
                    "total": "8"
                },
                "professor": "NEWMAN J"
            }
        }
    },
    "PROS": {
        "647": {
            "600": {
                "grade_amount": {
                    "A": "6",
                    "B": "0",
                    "C": "0",
                    "D": "0",
                    "F": "0"
                },
                "grade_percentage": {
                    "A": "100.00",
                    "B": "0.00",
                    "C": "0.00",
                    "D": "0.00",
                    "F": "0.00"
                },
                "total": "6",
                "gpa": "4.000",
                "other": {
                    "I": "0",
                    "S": "0",
                    "U": "0",
                    "Q": "0",
                    "X": "0",
                    "total": "6"
                },
                "professor": "CHO S"
            }
        }
    },
    "OMFS": {
        "610": {
            "600": {
                "grade_amount": {
                    "A": "10",
                    "B": "0",
                    "C": "0",
                    "D": "0",
                    "F": "0"
                },
                "grade_percentage": {
                    "A": "100.00",
                    "B": "0.00",
                    "C": "0.00",
                    "D": "0.00",
                    "F": "0.00"
                },
                "total": "10",
                "gpa": "4.000",
                "other": {
                    "I": "0",
                    "S": "0",
                    "U": "0",
                    "Q": "0",
                    "X": "0",
                    "total": "10"
                },
                "professor": "HENDERSON B"
            }
        },
        "650": {
            "600": {
                "grade_amount": {
                    "A": "8",
                    "B": "0",
                    "C": "0",
                    "D": "0",
                    "F": "0"
                },
                "grade_percentage": {
                    "A": "100.00",
                    "B": "0.00",
                    "C": "0.00",
                    "D": "0.00",
                    "F": "0.00"
                },
                "total": "8",
                "gpa": "4.000",
                "other": {
                    "I": "0",
                    "S": "0",
                    "U": "0",
                    "Q": "0",
                    "X": "0",
                    "total": "8"
                },
                "professor": "REDDY L"
            }
        }
    },
    "ORTH": {
        "602": {
            "600": {
                "grade_amount": {
                    "A": "6",
                    "B": "0",
                    "C": "0",
                    "D": "0",
                    "F": "0"
                },
                "grade_percentage": {
                    "A": "100.00",
                    "B": "0.00",
                    "C": "0.00",
                    "D": "0.00",
                    "F": "0.00"
                },
                "total": "6",
                "gpa": "0.000",
                "other": {
                    "I": "0",
                    "S": "0",
                    "U": "0",
                    "Q": "0",
                    "X": "0",
                    "total": "6"
                },
                "professor": "POLSON J"
            }
        },
        "606": {
            "600": {
                "grade_amount": {
                    "A": "6",
                    "B": "0",
                    "C": "0",
                    "D": "0",
                    "F": "0"
                },
                "grade_percentage": {
                    "A": "100.00",
                    "B": "0.00",
                    "C": "0.00",
                    "D": "0.00",
                    "F": "0.00"
                },
                "total": "6",
                "gpa": "0.000",
                "other": {
                    "I": "0",
                    "S": "0",
                    "U": "0",
                    "Q": "0",
                    "X": "0",
                    "total": "6"
                },
                "professor": "PARK Y"
            }
        },
        "608": {
            "600": {
                "grade_amount": {
                    "A": "6",
                    "B": "0",
                    "C": "0",
                    "D": "0",
                    "F": "0"
                },
                "grade_percentage": {
                    "A": "100.00",
                    "B": "0.00",
                    "C": "0.00",
                    "D": "0.00",
                    "F": "0.00"
                },
                "total": "6",
                "gpa": "0.000",
                "other": {
                    "I": "0",
                    "S": "0",
                    "U": "0",
                    "Q": "0",
                    "X": "0",
                    "total": "6"
                },
                "professor": "PARK Y"
            }
        },
        "610": {
            "600": {
                "grade_amount": {
                    "A": "6",
                    "B": "0",
                    "C": "0",
                    "D": "0",
                    "F": "0"
                },
                "grade_percentage": {
                    "A": "100.00",
                    "B": "0.00",
                    "C": "0.00",
                    "D": "0.00",
                    "F": "0.00"
                },
                "total": "6",
                "gpa": "4.000",
                "other": {
                    "I": "0",
                    "S": "0",
                    "U": "0",
                    "Q": "0",
                    "X": "0",
                    "total": "6"
                },
                "professor": "JACOB H"
            }
        },
        "613": {
            "600": {
                "grade_amount": {
                    "A": "4",
                    "B": "2",
                    "C": "0",
                    "D": "0",
                    "F": "0"
                },
                "grade_percentage": {
                    "A": "66.67",
                    "B": "33.33",
                    "C": "0.00",
                    "D": "0.00",
                    "F": "0.00"
                },
                "total": "6",
                "gpa": "3.666",
                "other": {
                    "I": "0",
                    "S": "0",
                    "U": "0",
                    "Q": "0",
                    "X": "0",
                    "total": "6"
                },
                "professor": "BUSCHANG P"
            }
        },
        "614": {
            "600": {
                "grade_amount": {
                    "A": "6",
                    "B": "0",
                    "C": "0",
                    "D": "0",
                    "F": "0"
                },
                "grade_percentage": {
                    "A": "100.00",
                    "B": "0.00",
                    "C": "0.00",
                    "D": "0.00",
                    "F": "0.00"
                },
                "total": "6",
                "gpa": "0.000",
                "other": {
                    "I": "0",
                    "S": "0",
                    "U": "0",
                    "Q": "0",
                    "X": "0",
                    "total": "6"
                },
                "professor": "TAYLOR R"
            }
        },
        "616": {
            "600": {
                "grade_amount": {
                    "A": "6",
                    "B": "0",
                    "C": "0",
                    "D": "0",
                    "F": "0"
                },
                "grade_percentage": {
                    "A": "100.00",
                    "B": "0.00",
                    "C": "0.00",
                    "D": "0.00",
                    "F": "0.00"
                },
                "total": "6",
                "gpa": "0.000",
                "other": {
                    "I": "0",
                    "S": "0",
                    "U": "0",
                    "Q": "0",
                    "X": "0",
                    "total": "6"
                },
                "professor": "TAYLOR R"
            }
        },
        "618": {
            "600": {
                "grade_amount": {
                    "A": "6",
                    "B": "0",
                    "C": "0",
                    "D": "0",
                    "F": "0"
                },
                "grade_percentage": {
                    "A": "100.00",
                    "B": "0.00",
                    "C": "0.00",
                    "D": "0.00",
                    "F": "0.00"
                },
                "total": "6",
                "gpa": "0.000",
                "other": {
                    "I": "0",
                    "S": "0",
                    "U": "0",
                    "Q": "0",
                    "X": "0",
                    "total": "6"
                },
                "professor": "TAYLOR R"
            }
        },
        "622": {
            "600": {
                "grade_amount": {
                    "A": "6",
                    "B": "0",
                    "C": "0",
                    "D": "0",
                    "F": "0"
                },
                "grade_percentage": {
                    "A": "100.00",
                    "B": "0.00",
                    "C": "0.00",
                    "D": "0.00",
                    "F": "0.00"
                },
                "total": "6",
                "gpa": "4.000",
                "other": {
                    "I": "0",
                    "S": "0",
                    "U": "0",
                    "Q": "0",
                    "X": "0",
                    "total": "6"
                },
                "professor": "TADLOCK L"
            }
        },
        "625": {
            "600": {
                "grade_amount": {
                    "A": "6",
                    "B": "0",
                    "C": "0",
                    "D": "0",
                    "F": "0"
                },
                "grade_percentage": {
                    "A": "100.00",
                    "B": "0.00",
                    "C": "0.00",
                    "D": "0.00",
                    "F": "0.00"
                },
                "total": "6",
                "gpa": "4.000",
                "other": {
                    "I": "0",
                    "S": "0",
                    "U": "0",
                    "Q": "0",
                    "X": "0",
                    "total": "6"
                },
                "professor": "TADLOCK L"
            }
        },
        "628": {
            "600": {
                "grade_amount": {
                    "A": "6",
                    "B": "0",
                    "C": "0",
                    "D": "0",
                    "F": "0"
                },
                "grade_percentage": {
                    "A": "100.00",
                    "B": "0.00",
                    "C": "0.00",
                    "D": "0.00",
                    "F": "0.00"
                },
                "total": "6",
                "gpa": "4.000",
                "other": {
                    "I": "0",
                    "S": "0",
                    "U": "0",
                    "Q": "0",
                    "X": "0",
                    "total": "6"
                },
                "professor": "TADLOCK L"
            }
        },
        "630": {
            "600": {
                "grade_amount": {
                    "A": "6",
                    "B": "0",
                    "C": "0",
                    "D": "0",
                    "F": "0"
                },
                "grade_percentage": {
                    "A": "100.00",
                    "B": "0.00",
                    "C": "0.00",
                    "D": "0.00",
                    "F": "0.00"
                },
                "total": "6",
                "gpa": "4.000",
                "other": {
                    "I": "0",
                    "S": "0",
                    "U": "0",
                    "Q": "0",
                    "X": "0",
                    "total": "6"
                },
                "professor": "TADLOCK L"
            }
        },
        "635": {
            "600": {
                "grade_amount": {
                    "A": "6",
                    "B": "0",
                    "C": "0",
                    "D": "0",
                    "F": "0"
                },
                "grade_percentage": {
                    "A": "100.00",
                    "B": "0.00",
                    "C": "0.00",
                    "D": "0.00",
                    "F": "0.00"
                },
                "total": "6",
                "gpa": "4.000",
                "other": {
                    "I": "0",
                    "S": "0",
                    "U": "0",
                    "Q": "0",
                    "X": "0",
                    "total": "6"
                },
                "professor": "BUSCHANG P"
            }
        },
        "638": {
            "600": {
                "grade_amount": {
                    "A": "6",
                    "B": "0",
                    "C": "0",
                    "D": "0",
                    "F": "0"
                },
                "grade_percentage": {
                    "A": "100.00",
                    "B": "0.00",
                    "C": "0.00",
                    "D": "0.00",
                    "F": "0.00"
                },
                "total": "6",
                "gpa": "4.000",
                "other": {
                    "I": "0",
                    "S": "0",
                    "U": "0",
                    "Q": "0",
                    "X": "0",
                    "total": "6"
                },
                "professor": "BUSCHANG P"
            }
        },
        "640": {
            "600": {
                "grade_amount": {
                    "A": "3",
                    "B": "3",
                    "C": "0",
                    "D": "0",
                    "F": "0"
                },
                "grade_percentage": {
                    "A": "50.00",
                    "B": "50.00",
                    "C": "0.00",
                    "D": "0.00",
                    "F": "0.00"
                },
                "total": "6",
                "gpa": "3.500",
                "other": {
                    "I": "0",
                    "S": "0",
                    "U": "0",
                    "Q": "0",
                    "X": "0",
                    "total": "6"
                },
                "professor": "TAYLOR R"
            }
        },
        "642": {
            "600": {
                "grade_amount": {
                    "A": "6",
                    "B": "0",
                    "C": "0",
                    "D": "0",
                    "F": "0"
                },
                "grade_percentage": {
                    "A": "100.00",
                    "B": "0.00",
                    "C": "0.00",
                    "D": "0.00",
                    "F": "0.00"
                },
                "total": "6",
                "gpa": "4.000",
                "other": {
                    "I": "0",
                    "S": "0",
                    "U": "0",
                    "Q": "0",
                    "X": "0",
                    "total": "6"
                },
                "professor": "TAYLOR R"
            }
        },
        "648": {
            "600": {
                "grade_amount": {
                    "A": "6",
                    "B": "0",
                    "C": "0",
                    "D": "0",
                    "F": "0"
                },
                "grade_percentage": {
                    "A": "100.00",
                    "B": "0.00",
                    "C": "0.00",
                    "D": "0.00",
                    "F": "0.00"
                },
                "total": "6",
                "gpa": "4.000",
                "other": {
                    "I": "0",
                    "S": "0",
                    "U": "0",
                    "Q": "0",
                    "X": "0",
                    "total": "6"
                },
                "professor": "GLENN G"
            }
        },
        "651": {
            "600": {
                "grade_amount": {
                    "A": "6",
                    "B": "0",
                    "C": "0",
                    "D": "0",
                    "F": "0"
                },
                "grade_percentage": {
                    "A": "100.00",
                    "B": "0.00",
                    "C": "0.00",
                    "D": "0.00",
                    "F": "0.00"
                },
                "total": "6",
                "gpa": "4.000",
                "other": {
                    "I": "0",
                    "S": "0",
                    "U": "0",
                    "Q": "0",
                    "X": "0",
                    "total": "6"
                },
                "professor": "GLENN G"
            }
        },
        "654": {
            "600": {
                "grade_amount": {
                    "A": "6",
                    "B": "0",
                    "C": "0",
                    "D": "0",
                    "F": "0"
                },
                "grade_percentage": {
                    "A": "100.00",
                    "B": "0.00",
                    "C": "0.00",
                    "D": "0.00",
                    "F": "0.00"
                },
                "total": "6",
                "gpa": "4.000",
                "other": {
                    "I": "0",
                    "S": "0",
                    "U": "0",
                    "Q": "0",
                    "X": "0",
                    "total": "6"
                },
                "professor": "GLENN G"
            }
        }
    },
    "PEDD": {
        "612": {
            "600": {
                "grade_amount": {
                    "A": "10",
                    "B": "0",
                    "C": "0",
                    "D": "0",
                    "F": "0"
                },
                "grade_percentage": {
                    "A": "100.00",
                    "B": "0.00",
                    "C": "0.00",
                    "D": "0.00",
                    "F": "0.00"
                },
                "total": "10",
                "gpa": "4.000",
                "other": {
                    "I": "0",
                    "S": "0",
                    "U": "0",
                    "Q": "0",
                    "X": "0",
                    "total": "10"
                },
                "professor": "KERINS C"
            }
        },
        "615": {
            "600": {
                "grade_amount": {
                    "A": "11",
                    "B": "0",
                    "C": "0",
                    "D": "0",
                    "F": "0"
                },
                "grade_percentage": {
                    "A": "100.00",
                    "B": "0.00",
                    "C": "0.00",
                    "D": "0.00",
                    "F": "0.00"
                },
                "total": "11",
                "gpa": "4.000",
                "other": {
                    "I": "0",
                    "S": "0",
                    "U": "0",
                    "Q": "0",
                    "X": "0",
                    "total": "11"
                },
                "professor": "KERINS C"
            }
        },
        "622": {
            "600": {
                "grade_amount": {
                    "A": "10",
                    "B": "0",
                    "C": "0",
                    "D": "0",
                    "F": "0"
                },
                "grade_percentage": {
                    "A": "100.00",
                    "B": "0.00",
                    "C": "0.00",
                    "D": "0.00",
                    "F": "0.00"
                },
                "total": "10",
                "gpa": "4.000",
                "other": {
                    "I": "0",
                    "S": "0",
                    "U": "0",
                    "Q": "0",
                    "X": "0",
                    "total": "10"
                },
                "professor": "KERINS C"
            }
        },
        "625": {
            "600": {
                "grade_amount": {
                    "A": "12",
                    "B": "0",
                    "C": "0",
                    "D": "0",
                    "F": "0"
                },
                "grade_percentage": {
                    "A": "100.00",
                    "B": "0.00",
                    "C": "0.00",
                    "D": "0.00",
                    "F": "0.00"
                },
                "total": "12",
                "gpa": "4.000",
                "other": {
                    "I": "0",
                    "S": "0",
                    "U": "0",
                    "Q": "0",
                    "X": "0",
                    "total": "12"
                },
                "professor": "KERINS C"
            }
        }
    },
    "PERI": {
        "650": {
            "600": {
                "grade_amount": {
                    "A": "6",
                    "B": "1",
                    "C": "0",
                    "D": "0",
                    "F": "0"
                },
                "grade_percentage": {
                    "A": "85.71",
                    "B": "14.29",
                    "C": "0.00",
                    "D": "0.00",
                    "F": "0.00"
                },
                "total": "7",
                "gpa": "3.857",
                "other": {
                    "I": "0",
                    "S": "0",
                    "U": "0",
                    "Q": "0",
                    "X": "0",
                    "total": "7"
                },
                "professor": "FALLAH A"
            }
        }
    }
}