{
    "VMID": {
        "935": {
            "301": {
                "grade_amount": {
                    "A": "137",
                    "B": "0",
                    "C": "0",
                    "D": "0",
                    "F": "0"
                },
                "grade_percentage": {
                    "A": "100.00",
                    "B": "0.00",
                    "C": "0.00",
                    "D": "0.00",
                    "F": "0.00"
                },
                "total": "137",
                "gpa": "4.000",
                "other": {
                    "I": "0",
                    "S": "0",
                    "U": "0",
                    "Q": "0",
                    "X": "0",
                    "total": "137"
                },
                "professor": "STICKNEY M"
            }
        },
        "989": {
            "321": {
                "grade_amount": {
                    "A": "11",
                    "B": "0",
                    "C": "0",
                    "D": "0",
                    "F": "0"
                },
                "grade_percentage": {
                    "A": "100.00",
                    "B": "0.00",
                    "C": "0.00",
                    "D": "0.00",
                    "F": "0.00"
                },
                "total": "11",
                "gpa": "4.000",
                "other": {
                    "I": "0",
                    "S": "0",
                    "U": "0",
                    "Q": "0",
                    "X": "0",
                    "total": "11"
                },
                "professor": "TAYCE J"
            }
        }
    },
    "VIBS": {
        "910": {
            "301": {
                "grade_amount": {
                    "A": "38",
                    "B": "74",
                    "C": "40",
                    "D": "6",
                    "F": "1"
                },
                "grade_percentage": {
                    "A": "23.90",
                    "B": "46.54",
                    "C": "25.16",
                    "D": "3.77",
                    "F": "0.63"
                },
                "total": "159",
                "gpa": "2.893",
                "other": {
                    "I": "0",
                    "S": "0",
                    "U": "0",
                    "Q": "0",
                    "X": "0",
                    "total": "159"
                },
                "professor": "HOFFMAN A"
            }
        },
        "911": {
            "301": {
                "grade_amount": {
                    "A": "90",
                    "B": "63",
                    "C": "6",
                    "D": "0",
                    "F": "0"
                },
                "grade_percentage": {
                    "A": "56.60",
                    "B": "39.62",
                    "C": "3.77",
                    "D": "0.00",
                    "F": "0.00"
                },
                "total": "159",
                "gpa": "3.528",
                "other": {
                    "I": "0",
                    "S": "0",
                    "U": "0",
                    "Q": "0",
                    "X": "0",
                    "total": "159"
                },
                "professor": "KNEESE D"
            }
        },
        "928": {
            "300": {
                "grade_amount": {
                    "A": "81",
                    "B": "60",
                    "C": "2",
                    "D": "0",
                    "F": "0"
                },
                "grade_percentage": {
                    "A": "56.64",
                    "B": "41.96",
                    "C": "1.40",
                    "D": "0.00",
                    "F": "0.00"
                },
                "total": "143",
                "gpa": "3.552",
                "other": {
                    "I": "0",
                    "S": "0",
                    "U": "0",
                    "Q": "0",
                    "X": "0",
                    "total": "143"
                },
                "professor": "BUDKE C"
            }
        },
        "936": {
            "301": {
                "grade_amount": {
                    "A": "156",
                    "B": "3",
                    "C": "0",
                    "D": "0",
                    "F": "0"
                },
                "grade_percentage": {
                    "A": "98.11",
                    "B": "1.89",
                    "C": "0.00",
                    "D": "0.00",
                    "F": "0.00"
                },
                "total": "159",
                "gpa": "3.981",
                "other": {
                    "I": "0",
                    "S": "0",
                    "U": "0",
                    "Q": "0",
                    "X": "0",
                    "total": "159"
                },
                "professor": "VEMULAPALLI T"
            }
        }
    },
    "VLCS": {
        "925": {
            "301": {
                "grade_amount": {
                    "A": "28",
                    "B": "89",
                    "C": "19",
                    "D": "1",
                    "F": "0"
                },
                "grade_percentage": {
                    "A": "20.44",
                    "B": "64.96",
                    "C": "13.87",
                    "D": "0.73",
                    "F": "0.00"
                },
                "total": "137",
                "gpa": "3.051",
                "other": {
                    "I": "0",
                    "S": "0",
                    "U": "0",
                    "Q": "0",
                    "X": "0",
                    "total": "137"
                },
                "professor": "VOGES A"
            }
        },
        "948": {
            "302": {
                "grade_amount": {
                    "A": "31",
                    "B": "0",
                    "C": "0",
                    "D": "0",
                    "F": "0"
                },
                "grade_percentage": {
                    "A": "100.00",
                    "B": "0.00",
                    "C": "0.00",
                    "D": "0.00",
                    "F": "0.00"
                },
                "total": "31",
                "gpa": "4.000",
                "other": {
                    "I": "0",
                    "S": "0",
                    "U": "0",
                    "Q": "0",
                    "X": "0",
                    "total": "31"
                },
                "professor": "DOMINGUEZ B"
            },
            "321": {
                "grade_amount": {
                    "A": "50",
                    "B": "0",
                    "C": "0",
                    "D": "0",
                    "F": "0"
                },
                "grade_percentage": {
                    "A": "100.00",
                    "B": "0.00",
                    "C": "0.00",
                    "D": "0.00",
                    "F": "0.00"
                },
                "total": "50",
                "gpa": "4.000",
                "other": {
                    "I": "0",
                    "S": "0",
                    "U": "0",
                    "Q": "0",
                    "X": "0",
                    "total": "50"
                },
                "professor": "CHAFFIN M"
            },
            "322": {
                "grade_amount": {
                    "A": "52",
                    "B": "4",
                    "C": "0",
                    "D": "0",
                    "F": "0"
                },
                "grade_percentage": {
                    "A": "92.86",
                    "B": "7.14",
                    "C": "0.00",
                    "D": "0.00",
                    "F": "0.00"
                },
                "total": "56",
                "gpa": "3.928",
                "other": {
                    "I": "0",
                    "S": "0",
                    "U": "0",
                    "Q": "0",
                    "X": "0",
                    "total": "56"
                },
                "professor": "CERFOGLI J"
            }
        },
        "956": {
            "301": {
                "grade_amount": {
                    "A": "57",
                    "B": "77",
                    "C": "3",
                    "D": "0",
                    "F": "0"
                },
                "grade_percentage": {
                    "A": "41.61",
                    "B": "56.20",
                    "C": "2.19",
                    "D": "0.00",
                    "F": "0.00"
                },
                "total": "137",
                "gpa": "3.394",
                "other": {
                    "I": "0",
                    "S": "0",
                    "U": "0",
                    "Q": "0",
                    "X": "0",
                    "total": "137"
                },
                "professor": "WATKINS J"
            }
        },
        "958": {
            "301": {
                "grade_amount": {
                    "A": "25",
                    "B": "4",
                    "C": "0",
                    "D": "0",
                    "F": "0"
                },
                "grade_percentage": {
                    "A": "86.21",
                    "B": "13.79",
                    "C": "0.00",
                    "D": "0.00",
                    "F": "0.00"
                },
                "total": "29",
                "gpa": "3.862",
                "other": {
                    "I": "0",
                    "S": "0",
                    "U": "0",
                    "Q": "0",
                    "X": "0",
                    "total": "29"
                },
                "professor": "NAGY D"
            }
        },
        "959": {
            "301": {
                "grade_amount": {
                    "A": "18",
                    "B": "5",
                    "C": "0",
                    "D": "0",
                    "F": "0"
                },
                "grade_percentage": {
                    "A": "78.26",
                    "B": "21.74",
                    "C": "0.00",
                    "D": "0.00",
                    "F": "0.00"
                },
                "total": "23",
                "gpa": "3.782",
                "other": {
                    "I": "0",
                    "S": "0",
                    "U": "0",
                    "Q": "0",
                    "X": "0",
                    "total": "23"
                },
                "professor": "COLEMAN M"
            }
        }
    },
    "VTPP": {
        "910": {
            "301": {
                "grade_amount": {
                    "A": "77",
                    "B": "61",
                    "C": "17",
                    "D": "3",
                    "F": "1"
                },
                "grade_percentage": {
                    "A": "48.43",
                    "B": "38.36",
                    "C": "10.69",
                    "D": "1.89",
                    "F": "0.63"
                },
                "total": "159",
                "gpa": "3.320",
                "other": {
                    "I": "0",
                    "S": "0",
                    "U": "0",
                    "Q": "0",
                    "X": "0",
                    "total": "159"
                },
                "professor": "STEWART R"
            }
        },
        "914": {
            "301": {
                "grade_amount": {
                    "A": "132",
                    "B": "26",
                    "C": "1",
                    "D": "0",
                    "F": "0"
                },
                "grade_percentage": {
                    "A": "83.02",
                    "B": "16.35",
                    "C": "0.63",
                    "D": "0.00",
                    "F": "0.00"
                },
                "total": "159",
                "gpa": "3.823",
                "other": {
                    "I": "0",
                    "S": "0",
                    "U": "0",
                    "Q": "0",
                    "X": "0",
                    "total": "159"
                },
                "professor": "BLUE M"
            }
        },
        "924": {
            "300": {
                "grade_amount": {
                    "A": "52",
                    "B": "69",
                    "C": "22",
                    "D": "0",
                    "F": "0"
                },
                "grade_percentage": {
                    "A": "36.36",
                    "B": "48.25",
                    "C": "15.38",
                    "D": "0.00",
                    "F": "0.00"
                },
                "total": "143",
                "gpa": "3.209",
                "other": {
                    "I": "0",
                    "S": "0",
                    "U": "0",
                    "Q": "0",
                    "X": "0",
                    "total": "143"
                },
                "professor": "FAJT V"
            }
        },
        "948": {
            "302": {
                "grade_amount": {
                    "A": "9",
                    "B": "4",
                    "C": "0",
                    "D": "0",
                    "F": "0"
                },
                "grade_percentage": {
                    "A": "69.23",
                    "B": "30.77",
                    "C": "0.00",
                    "D": "0.00",
                    "F": "0.00"
                },
                "total": "13",
                "gpa": "3.692",
                "other": {
                    "I": "0",
                    "S": "0",
                    "U": "0",
                    "Q": "0",
                    "X": "0",
                    "total": "13"
                },
                "professor": "FAJT V"
            }
        }
    },
    "VSCS": {
        "910": {
            "301": {
                "grade_amount": {
                    "A": "21",
                    "B": "115",
                    "C": "22",
                    "D": "1",
                    "F": "0"
                },
                "grade_percentage": {
                    "A": "13.21",
                    "B": "72.33",
                    "C": "13.84",
                    "D": "0.63",
                    "F": "0.00"
                },
                "total": "159",
                "gpa": "2.981",
                "other": {
                    "I": "0",
                    "S": "0",
                    "U": "0",
                    "Q": "0",
                    "X": "0",
                    "total": "159"
                },
                "professor": "ECKMAN S"
            }
        },
        "926": {
            "300": {
                "grade_amount": {
                    "A": "52",
                    "B": "76",
                    "C": "13",
                    "D": "0",
                    "F": "1"
                },
                "grade_percentage": {
                    "A": "36.62",
                    "B": "53.52",
                    "C": "9.15",
                    "D": "0.00",
                    "F": "0.70"
                },
                "total": "142",
                "gpa": "3.253",
                "other": {
                    "I": "1",
                    "S": "0",
                    "U": "0",
                    "Q": "0",
                    "X": "0",
                    "total": "143"
                },
                "professor": "MCCOOL K"
            }
        },
        "934": {
            "301": {
                "grade_amount": {
                    "A": "80",
                    "B": "54",
                    "C": "2",
                    "D": "0",
                    "F": "0"
                },
                "grade_percentage": {
                    "A": "58.82",
                    "B": "39.71",
                    "C": "1.47",
                    "D": "0.00",
                    "F": "0.00"
                },
                "total": "136",
                "gpa": "3.573",
                "other": {
                    "I": "1",
                    "S": "0",
                    "U": "0",
                    "Q": "0",
                    "X": "0",
                    "total": "137"
                },
                "professor": "SCALLAN E"
            }
        },
        "948": {
            "301": {
                "grade_amount": {
                    "A": "74",
                    "B": "2",
                    "C": "0",
                    "D": "0",
                    "F": "0"
                },
                "grade_percentage": {
                    "A": "97.37",
                    "B": "2.63",
                    "C": "0.00",
                    "D": "0.00",
                    "F": "0.00"
                },
                "total": "76",
                "gpa": "3.973",
                "other": {
                    "I": "0",
                    "S": "0",
                    "U": "0",
                    "Q": "0",
                    "X": "0",
                    "total": "76"
                },
                "professor": "HEATLEY J"
            },
            "302": {
                "grade_amount": {
                    "A": "66",
                    "B": "0",
                    "C": "0",
                    "D": "0",
                    "F": "0"
                },
                "grade_percentage": {
                    "A": "100.00",
                    "B": "0.00",
                    "C": "0.00",
                    "D": "0.00",
                    "F": "0.00"
                },
                "total": "66",
                "gpa": "4.000",
                "other": {
                    "I": "0",
                    "S": "0",
                    "U": "0",
                    "Q": "0",
                    "X": "0",
                    "total": "66"
                },
                "professor": "DAVIDSON J"
            },
            "303": {
                "grade_amount": {
                    "A": "24",
                    "B": "0",
                    "C": "0",
                    "D": "0",
                    "F": "0"
                },
                "grade_percentage": {
                    "A": "100.00",
                    "B": "0.00",
                    "C": "0.00",
                    "D": "0.00",
                    "F": "0.00"
                },
                "total": "24",
                "gpa": "4.000",
                "other": {
                    "I": "0",
                    "S": "0",
                    "U": "0",
                    "Q": "0",
                    "X": "0",
                    "total": "24"
                },
                "professor": "TAYCE J"
            },
            "321": {
                "grade_amount": {
                    "A": "84",
                    "B": "0",
                    "C": "0",
                    "D": "0",
                    "F": "0"
                },
                "grade_percentage": {
                    "A": "100.00",
                    "B": "0.00",
                    "C": "0.00",
                    "D": "0.00",
                    "F": "0.00"
                },
                "total": "84",
                "gpa": "4.000",
                "other": {
                    "I": "0",
                    "S": "0",
                    "U": "0",
                    "Q": "0",
                    "X": "0",
                    "total": "84"
                },
                "professor": "AUDREY C"
            },
            "322": {
                "grade_amount": {
                    "A": "35",
                    "B": "0",
                    "C": "0",
                    "D": "0",
                    "F": "0"
                },
                "grade_percentage": {
                    "A": "100.00",
                    "B": "0.00",
                    "C": "0.00",
                    "D": "0.00",
                    "F": "0.00"
                },
                "total": "35",
                "gpa": "4.000",
                "other": {
                    "I": "0",
                    "S": "0",
                    "U": "0",
                    "Q": "0",
                    "X": "0",
                    "total": "35"
                },
                "professor": "WARRY E"
            },
            "323": {
                "grade_amount": {
                    "A": "24",
                    "B": "13",
                    "C": "0",
                    "D": "0",
                    "F": "0"
                },
                "grade_percentage": {
                    "A": "64.86",
                    "B": "35.14",
                    "C": "0.00",
                    "D": "0.00",
                    "F": "0.00"
                },
                "total": "37",
                "gpa": "3.648",
                "other": {
                    "I": "0",
                    "S": "0",
                    "U": "0",
                    "Q": "0",
                    "X": "0",
                    "total": "37"
                },
                "professor": "HEATLEY J"
            }
        },
        "956": {
            "301": {
                "grade_amount": {
                    "A": "35",
                    "B": "75",
                    "C": "26",
                    "D": "1",
                    "F": "0"
                },
                "grade_percentage": {
                    "A": "25.55",
                    "B": "54.74",
                    "C": "18.98",
                    "D": "0.73",
                    "F": "0.00"
                },
                "total": "137",
                "gpa": "3.051",
                "other": {
                    "I": "0",
                    "S": "0",
                    "U": "0",
                    "Q": "0",
                    "X": "0",
                    "total": "137"
                },
                "professor": "HESELTINE J"
            }
        },
        "958": {
            "301": {
                "grade_amount": {
                    "A": "42",
                    "B": "42",
                    "C": "1",
                    "D": "0",
                    "F": "0"
                },
                "grade_percentage": {
                    "A": "49.41",
                    "B": "49.41",
                    "C": "1.18",
                    "D": "0.00",
                    "F": "0.00"
                },
                "total": "85",
                "gpa": "3.482",
                "other": {
                    "I": "0",
                    "S": "0",
                    "U": "0",
                    "Q": "0",
                    "X": "0",
                    "total": "85"
                },
                "professor": "BARNES K"
            }
        }
    },
    "VTPB": {
        "910": {
            "301": {
                "grade_amount": {
                    "A": "63",
                    "B": "70",
                    "C": "26",
                    "D": "0",
                    "F": "0"
                },
                "grade_percentage": {
                    "A": "39.62",
                    "B": "44.03",
                    "C": "16.35",
                    "D": "0.00",
                    "F": "0.00"
                },
                "total": "159",
                "gpa": "3.232",
                "other": {
                    "I": "0",
                    "S": "0",
                    "U": "0",
                    "Q": "0",
                    "X": "0",
                    "total": "159"
                },
                "professor": "VEMULAPALLI R"
            }
        },
        "923": {
            "300": {
                "grade_amount": {
                    "A": "47",
                    "B": "73",
                    "C": "22",
                    "D": "0",
                    "F": "1"
                },
                "grade_percentage": {
                    "A": "32.87",
                    "B": "51.05",
                    "C": "15.38",
                    "D": "0.00",
                    "F": "0.70"
                },
                "total": "143",
                "gpa": "3.153",
                "other": {
                    "I": "0",
                    "S": "0",
                    "U": "0",
                    "Q": "0",
                    "X": "0",
                    "total": "143"
                },
                "professor": "PORTER B"
            }
        },
        "927": {
            "300": {
                "grade_amount": {
                    "A": "66",
                    "B": "71",
                    "C": "5",
                    "D": "1",
                    "F": "0"
                },
                "grade_percentage": {
                    "A": "46.15",
                    "B": "49.65",
                    "C": "3.50",
                    "D": "0.70",
                    "F": "0.00"
                },
                "total": "143",
                "gpa": "3.412",
                "other": {
                    "I": "0",
                    "S": "0",
                    "U": "0",
                    "Q": "0",
                    "X": "0",
                    "total": "143"
                },
                "professor": "RUSSELL K"
            }
        },
        "930": {
            "300": {
                "grade_amount": {
                    "A": "95",
                    "B": "47",
                    "C": "1",
                    "D": "0",
                    "F": "0"
                },
                "grade_percentage": {
                    "A": "66.43",
                    "B": "32.87",
                    "C": "0.70",
                    "D": "0.00",
                    "F": "0.00"
                },
                "total": "143",
                "gpa": "3.657",
                "other": {
                    "I": "0",
                    "S": "0",
                    "U": "0",
                    "Q": "0",
                    "X": "0",
                    "total": "143"
                },
                "professor": "LAWHON S"
            }
        },
        "948": {
            "302": {
                "grade_amount": {
                    "A": "76",
                    "B": "0",
                    "C": "0",
                    "D": "0",
                    "F": "0"
                },
                "grade_percentage": {
                    "A": "100.00",
                    "B": "0.00",
                    "C": "0.00",
                    "D": "0.00",
                    "F": "0.00"
                },
                "total": "76",
                "gpa": "4.000",
                "other": {
                    "I": "0",
                    "S": "0",
                    "U": "0",
                    "Q": "0",
                    "X": "0",
                    "total": "76"
                },
                "professor": "COOK W"
            }
        }
    }
}